garc/__init__.py
garc/client.py
garc/command.py
garc-1.1.3.dist-info/METADATA
garc-1.1.3.dist-info/RECORD
garc-1.1.3.dist-info/WHEEL
garc-1.1.3.dist-info/entry_points.txt
garc-1.1.3.dist-info/top_level.txt
