Metadata-Version: 2.1
Name: garc
Version: 1.1.3
Summary: Archive Gab.ai posts from the command line
Home-page: https://github.com/ChrisStevens/garc
Author: Chris Stevens
Author-email: chris.stevens@mail.utoronto.ca
License: UNKNOWN
Platform: UNKNOWN
Requires-Dist: pytest
Requires-Dist: python-dateutil
Requires-Dist: requests
Requires-Dist: unicodecsv
Requires-Dist: mock
Requires-Dist: beautifulsoup4
